miunlock/__init__.py
miunlock/__main__.py
miunlock/aes.py
miunlock/commands.py
miunlock/config.py
miunlock/service.py
miunlock/unlock.py
miunlock/utils.py
miunlock/login/auth_utils.py
miunlock/login/captcha_verify.py
miunlock/login/login.py
miunlock/login/verification.py
miunlock/region/config.py
miunlock/region/domain.py
miunlock/region/region.py
miunlock/region/region_config.py
miunlock-1.6.1.dist-info/licenses/LICENSE
miunlock-1.6.1.dist-info/METADATA
miunlock-1.6.1.dist-info/WHEEL
miunlock-1.6.1.dist-info/entry_points.txt
miunlock-1.6.1.dist-info/top_level.txt
miunlock-1.6.1.dist-info/RECORD
