Metadata-Version: 2.4
Name: miunlock
Version: 1.6.1
Summary: Retrieve Xiaomi encryptData(token) to unlock bootloader
Author: offici5l
License:                                  Apache License
Project-URL: Repository, https://github.com/offici5l/MiUnlockTool
Keywords: xiaomi,miunlock,MiUnlockTool,bootloader,unlock,MIUI,HyperOS,Tools
Classifier: Development Status :: 5 - Production/Stable
Classifier: Programming Language :: Python :: 3
Classifier: License :: OSI Approved :: Apache Software License
Classifier: Operating System :: OS Independent
Requires-Python: >=3.7
License-File: LICENSE
Requires-Dist: requests
Dynamic: license-file
